shoreline/__init__.py
shoreline/errors.py
shoreline/utils/__init__.py
shoreline/utils/clipping.py
shoreline/utils/kriging.py
shoreline/utils/perpendicular.py
shoreline/utils/piecewise.py
shoreline/utils/projection.py
shoreline/utils/resolution.py
shoreline/utils/shoal_break.py
shoreline/utils/smoother.py
shoreline-0.2.2.dist-info/licenses/LICENSE.md
shoreline-0.2.2.dist-info/METADATA
shoreline-0.2.2.dist-info/WHEEL
shoreline-0.2.2.dist-info/top_level.txt
shoreline-0.2.2.dist-info/RECORD
